exceltotable/1onlinechecksum.py
exceltotable/MYS_LT.py
exceltotable/RetailProConsumerLoyaltyTransactionChecksum_SGP.py
exceltotable/SG_LT.py
exceltotable/__init__.py
exceltotable/csmchecksum.py
exceltotable/csvLoyalty.py
exceltotable/db1.py
exceltotable/demo.py
exceltotable/filetodb.py
exceltotable/frontier_CTL.py
exceltotable/frontiers.py
exceltotable/frontiesTodb.py
exceltotable/frontiesTodbcsv.py
exceltotable/frontiesTodbexcel.py
exceltotable/graph.py
exceltotable/login_outlook.py
exceltotable/loyalty.py
exceltotable/loyaltyls.py
exceltotable/ms_graph.py
exceltotable/offline.py
exceltotable/onlineauto.py
exceltotable-1.1.0.dist-info/METADATA
exceltotable-1.1.0.dist-info/WHEEL
exceltotable-1.1.0.dist-info/top_level.txt
exceltotable-1.1.0.dist-info/RECORD
